fixpath/__init__.py
fixpath-0.1.0.dist-info/LICENSE
fixpath-0.1.0.dist-info/METADATA
fixpath-0.1.0.dist-info/WHEEL
fixpath-0.1.0.dist-info/top_level.txt
fixpath-0.1.0.dist-info/RECORD
